{"info": {"isCASec": false, "isDelisted": false, "tempSuspendedSeries": [], "companyName": "Gateway Distriparks Limited", "industry": "TRAVEL AND TRANSPORT", "symbol": "GDL", "isSuspended": false, "isDebtSec": false, "isTop10": false, "debtSeries": [], "isETFSec": false, "isSLBSec": false, "isin": "INE852F01015", "isFNOSec": false, "identifier": "GDLEQN", "activeSeries": ["EQ"]}, "priceInfo": {"pPriceBand": "20", "lastPrice": 89.45, "previousClose": 90.25, "weekHighLow": {"maxDate": "29-Jan-2020", "max": 139.12, "minDate": "24-Mar-2020", "value": 89.45, "min": 69.61}, "vwap": 89.49, "pChange": -0.8864265927977807, "lowerCP": "72.20", "basePrice": 90.25, "close": 0, "upperCP": "108.30", "intraDayHighLow": {"max": 92.1, "value": 89.45, "min": 88.3}, "open": 91.7, "change": -0.7999999999999972}, "preOpenMarket": {"preopen": [{"iep": true, "price": 0, "buyQty": 0, "sellQty": 0}, {"price": 89.05, "buyQty": 200, "sellQty": 0}, {"price": 89.5, "buyQty": 360, "sellQty": 0}, {"price": 89.65, "buyQty": 300, "sellQty": 0}, {"price": 90, "buyQty": 70, "sellQty": 0}, {"price": 91.05, "buyQty": 200, "sellQty": 0}, {"price": 92.35, "buyQty": 0, "sellQty": 2}, {"price": 92.65, "buyQty": 0, "sellQty": 200}, {"price": 92.7, "buyQty": 0, "sellQty": 600}, {"price": 92.8, "buyQty": 0, "sellQty": 500}, {"price": 93, "buyQty": 0, "sellQty": 500}], "totalBuyQuantity": 19000, "totalSellQuantity": 104772, "lastUpdateTime": "18-Sep-2020 09:07:20", "ato": {"sell": 0, "buy": 0}, "atoBuyQty": 0, "finalPrice": 90.25, "atoSellQty": 0, "finalQuantity": 0, "totalTradedVolume": 0, "IEP": 0}, "marketDeptOrderBook": {"totalSellQuantity": 0, "totalBuyQuantity": 1659, "bid": [{"price": 89.45, "quantity": 1659}, {"price": 0, "quantity": 0}, {"price": 0, "quantity": 0}, {"price": 0, "quantity": 0}, {"price": 0, "quantity": 0}], "valueAtRisk": {"applicableMargin": 40, "extremeLossMargin": 3.5, "adhocMargin": 17.47, "indexVar": 0, "securityVar": 19.03, "varMargin": 19.03}, "tradeInfo": {"totalMarketCap": 111665.72, "impactCost": 0.42, "totalTradedVolume": 184896, "ffmc": 78865.084879, "totalTradedValue": 165.46}, "ask": [{"price": 0, "quantity": 0}, {"price": 0, "quantity": 0}, {"price": 0, "quantity": 0}, {"price": 0, "quantity": 0}, {"price": 0, "quantity": 0}]}, "noBlockDeals": true, "language": {"shortNamePunjabi": "\u0a17\u0a47\u0a1f\u0a35\u0a47 \u0a21\u0a3f\u0a38\u0a1f\u0a4d\u0a30\u0a40\u0a2a\u0a3e\u0a30\u0a15\u0a38 ", "shortName": "Gateway Distriparks ", "shortNameHindi": "\u0917\u0947\u091f\u0935\u0947 \u0921\u093f\u0938\u094d\u091f\u094d\u0930\u0940\u092a\u093e\u0930\u094d\u0915\u0938 ", "nameHindi": "\u0917\u0947\u091f\u0935\u0947 \u0921\u093f\u0938\u094d\u091f\u094d\u0930\u0940\u092a\u093e\u0930\u094d\u0915\u0938 \u0932\u093f\u092e\u093f\u091f\u0947\u0921", "namePunjabi": "\u0a17\u0a47\u0a1f\u0a35\u0a47 \u0a21\u0a3f\u0a38\u0a1f\u0a4d\u0a30\u0a40\u0a2a\u0a3e\u0a30\u0a15\u0a38 \u0a32\u0a3f\u0a2e\u0a1f\u0a3f\u0a21"}, "bulkBlockDeals": [{"name": "Session I"}, {"name": "Session II"}], "securityWiseDP": {"seriesRemarks": null, "quantityTraded": 108611, "secWiseDelPosDate": "18-SEP-2020 15:00:00", "deliveryToTradedQuantity": 83.84, "deliveryQuantity": 91057}, "securityInfo": {"derivatives": "No", "surveillance": "-", "sessionNo": "-", "classOfShare": "Equity", "faceValue": 10, "tradingStatus": "Active", "issuedCap": 124835908, "tradingSegment": "Normal Market", "boardStatus": "Main", "slb": "No"}, "metadata": {"status": "Listed", "lastUpdateTime": "18-Sep-2020 16:00:00", "listingDate": "31-Mar-2005", "series": "EQ", "symbol": "GDL", "pdSymbolPe": 11.05, "pdSectorPe": 70.21, "pdSectorInd": "NIFTY INFRASTRUCTURE                              ", "isin": "INE852F01015", "industry": "LOGISTICS SOLUTION PROVIDER"}}