{"info": {"isCASec": false, "isDelisted": false, "tempSuspendedSeries": ["BE", "W1"], "companyName": "Renaissance Global Limited", "symbol": "RGL", "isSuspended": false, "isDebtSec": false, "isTop10": false, "debtSeries": [], "isETFSec": false, "isSLBSec": false, "isin": "INE722H13011", "isFNOSec": false, "identifier": "RGLEQN", "activeSeries": ["EQ"]}, "priceInfo": {"pPriceBand": "20", "lastPrice": 260.5, "previousClose": 261.75, "weekHighLow": {"maxDate": "29-Jan-2020", "max": 408, "minDate": "22-May-2020", "value": 260.5, "min": 184.05}, "vwap": 262.22, "pChange": -0.4775549188156638, "lowerCP": "209.40", "basePrice": 261.75, "close": 0, "upperCP": "314.10", "intraDayHighLow": {"max": 267.95, "value": 260.5, "min": 260.5}, "open": 267.95, "change": -1.25}, "preOpenMarket": {"preopen": [{"price": 244.65, "buyQty": 250, "sellQty": 0}, {"price": 246, "buyQty": 1, "sellQty": 0}, {"price": 252.65, "buyQty": 125, "sellQty": 0}, {"price": 259, "buyQty": 1, "sellQty": 0}, {"iep": true, "price": 267.95, "buyQty": 0, "sellQty": 50}, {"price": 268, "buyQty": 0, "sellQty": 100}, {"price": 271.05, "buyQty": 0, "sellQty": 46}, {"price": 272, "buyQty": 0, "sellQty": 15}], "totalBuyQuantity": 1981, "totalSellQuantity": 1841, "lastUpdateTime": "18-Sep-2020 09:07:22", "ato": {"sell": 0, "buy": 2}, "atoBuyQty": 2, "finalPrice": 267.95, "atoSellQty": 0, "finalQuantity": 2, "totalTradedVolume": 2, "IEP": 267.95}, "marketDeptOrderBook": {"totalSellQuantity": 60, "totalBuyQuantity": 0, "bid": [{"price": 0, "quantity": 0}, {"price": 0, "quantity": 0}, {"price": 0, "quantity": 0}, {"price": 0, "quantity": 0}, {"price": 0, "quantity": 0}], "valueAtRisk": {"applicableMargin": 49.38, "extremeLossMargin": 3.5, "adhocMargin": 22.21, "indexVar": 0, "securityVar": 23.67, "varMargin": 23.67}, "tradeInfo": {"totalMarketCap": 49180.94, "impactCost": 1.81, "totalTradedVolume": 2375, "ffmc": 12344.79383, "totalTradedValue": 6.23}, "ask": [{"price": 261.55, "quantity": 60}, {"price": 0, "quantity": 0}, {"price": 0, "quantity": 0}, {"price": 0, "quantity": 0}, {"price": 0, "quantity": 0}]}, "noBlockDeals": true, "language": {"shortNamePunjabi": "\u0a30\u0a47\u0a28\u0a47\u0a38\u0a48\u0a02\u0a38 \u0a17\u0a32\u0a4b\u0a2c\u0a32 ", "shortName": "Renaissance Global ", "shortNameHindi": "\u0930\u0947\u0928\u0948\u0938\u094d\u0938\u0902\u0938 \u0917\u094d\u0932\u094b\u092c\u0932  ", "nameHindi": "\u0930\u0947\u0928\u0948\u0938\u094d\u0938\u0902\u0938 \u0917\u094d\u0932\u094b\u092c\u0932  \u0932\u093f\u092e\u093f\u091f\u0947\u0921", "namePunjabi": "\u0a30\u0a47\u0a28\u0a47\u0a38\u0a48\u0a02\u0a38 \u0a17\u0a32\u0a4b\u0a2c\u0a32 \u0a32\u0a3f\u0a2e\u0a1f\u0a3f\u0a21"}, "bulkBlockDeals": [{"name": "Session I"}, {"name": "Session II"}], "securityWiseDP": {"seriesRemarks": null, "quantityTraded": 2375, "secWiseDelPosDate": "18-SEP-2020 EOD", "deliveryToTradedQuantity": 35.83, "deliveryQuantity": 851}, "securityInfo": {"derivatives": "No", "surveillance": "-", "sessionNo": "-", "classOfShare": "Equity", "faceValue": 10, "tradingStatus": "Active", "issuedCap": 18879440, "tradingSegment": "Normal Market", "boardStatus": "Main", "slb": "No"}, "metadata": {"status": "Listed", "lastUpdateTime": "18-Sep-2020 16:00:00", "listingDate": "12-Dec-2007", "series": "EQ", "symbol": "RGL", "pdSymbolPe": "NA", "pdSectorPe": "NA", "pdSectorInd": "NA", "isin": "INE722H01016", "industry": "GEMS JEWELLERY AND WATCHES"}}