{"info": {"isCASec": false, "isDelisted": false, "tempSuspendedSeries": [], "companyName": "Shree Renuka Sugars Limited", "industry": "SUGAR", "symbol": "RENUKA", "isSuspended": false, "isDebtSec": false, "isTop10": false, "debtSeries": [], "isETFSec": false, "isSLBSec": false, "isin": "INE087H01022", "isFNOSec": false, "identifier": "RENUKAEQN", "activeSeries": ["EQ"]}, "priceInfo": {"pPriceBand": "5", "lastPrice": 9.25, "previousClose": 9.3, "weekHighLow": {"maxDate": "02-Jul-2020", "max": 12.25, "minDate": "25-Mar-2020", "value": 9.25, "min": 3.25}, "vwap": 9.38, "pChange": -0.5376344086021582, "lowerCP": "8.85", "basePrice": 9.3, "close": 0, "upperCP": "9.75", "intraDayHighLow": {"max": 9.7, "value": 9.25, "min": 9.2}, "open": 9.2, "change": -0.05000000000000071}, "preOpenMarket": {"preopen": [{"price": 9.1, "buyQty": 1000, "sellQty": 0}, {"price": 9.15, "buyQty": 1110, "sellQty": 0}, {"iep": true, "price": 9.2, "buyQty": 19600, "sellQty": 0}, {"price": 9.3, "buyQty": 351, "sellQty": 11}, {"price": 9.35, "buyQty": 0, "sellQty": 4715}, {"price": 9.45, "buyQty": 0, "sellQty": 20000}, {"price": 9.5, "buyQty": 0, "sellQty": 11}], "totalBuyQuantity": 97394, "totalSellQuantity": 266739, "lastUpdateTime": "18-Sep-2020 09:07:21", "ato": {"sell": 499, "buy": 0}, "atoBuyQty": 0, "finalPrice": 9.2, "atoSellQty": 499, "finalQuantity": 499, "totalTradedVolume": 499, "IEP": 9.2}, "marketDeptOrderBook": {"totalSellQuantity": 12164, "totalBuyQuantity": 0, "bid": [{"price": 0, "quantity": 0}, {"price": 0, "quantity": 0}, {"price": 0, "quantity": 0}, {"price": 0, "quantity": 0}, {"price": 0, "quantity": 0}], "valueAtRisk": {"applicableMargin": 40, "extremeLossMargin": 3.5, "adhocMargin": 13.05, "indexVar": 0, "securityVar": 23.45, "varMargin": 23.45}, "tradeInfo": {"totalMarketCap": 177305.78, "impactCost": 2.15, "totalTradedVolume": 830435, "ffmc": 74870.9615455, "totalTradedValue": 77.89}, "ask": [{"price": 9.3, "quantity": 12164}, {"price": 0, "quantity": 0}, {"price": 0, "quantity": 0}, {"price": 0, "quantity": 0}, {"price": 0, "quantity": 0}]}, "noBlockDeals": true, "language": {"shortNamePunjabi": "\u0a38\u0a3c\u0a4d\u0a30\u0a40 \u0a30\u0a47\u0a23\u0a41\u0a15\u0a3e \u0a38\u0a3c\u0a42\u0a17\u0a30\u0a1c\u0a3c ", "shortName": "Shree Renuka Sugars ", "shortNameHindi": "\u0936\u094d\u0930\u0940 \u0930\u0947\u0923\u0941\u0915\u093e \u0936\u0941\u0917\u0930\u094d\u0938 ", "nameHindi": "\u0936\u094d\u0930\u0940 \u0930\u0947\u0923\u0941\u0915\u093e \u0936\u0941\u0917\u0930\u094d\u0938 \u0932\u093f\u092e\u093f\u091f\u0947\u0921", "namePunjabi": "\u0a38\u0a3c\u0a4d\u0a30\u0a40 \u0a30\u0a47\u0a23\u0a41\u0a15\u0a3e \u0a38\u0a3c\u0a42\u0a17\u0a30\u0a1c\u0a3c \u0a32\u0a3f\u0a2e\u0a1f\u0a3f\u0a21"}, "bulkBlockDeals": [{"name": "Session I"}, {"name": "Session II"}], "securityWiseDP": {"seriesRemarks": null, "quantityTraded": 830435, "secWiseDelPosDate": "18-SEP-2020 EOD", "deliveryToTradedQuantity": 50.53, "deliveryQuantity": 419606}, "securityInfo": {"derivatives": "No", "surveillance": "-", "sessionNo": "-", "classOfShare": "Equity", "faceValue": 1, "tradingStatus": "Active", "issuedCap": 1916819292, "tradingSegment": "Normal Market", "boardStatus": "Main", "slb": "No"}, "metadata": {"status": "Listed", "lastUpdateTime": "18-Sep-2020 16:00:00", "listingDate": "31-Oct-2005", "series": "EQ", "symbol": "RENUKA", "pdSymbolPe": 0, "pdSectorPe": 38.89, "pdSectorInd": "NIFTY FMCG                                        ", "isin": "INE087H01022", "industry": "SUGAR"}}