{"info": {"isCASec": false, "isDelisted": false, "tempSuspendedSeries": [], "companyName": "Shreyans Industries Limited", "industry": "PAPER AND PAPER PRODUCTS", "symbol": "SHREYANIND", "isSuspended": false, "isDebtSec": false, "isTop10": false, "debtSeries": [], "isETFSec": false, "isSLBSec": false, "isin": "INE231C01019", "isFNOSec": false, "identifier": "SHREYANINDEQN", "activeSeries": ["EQ"]}, "priceInfo": {"pPriceBand": "20", "lastPrice": 79.5, "previousClose": 77.55, "weekHighLow": {"maxDate": "01-Oct-2019", "max": 154.35, "minDate": "19-Mar-2020", "value": 79.5, "min": 56.1}, "vwap": 78.92, "pChange": 2.5145067698259225, "lowerCP": "62.05", "basePrice": 77.55, "close": 0, "upperCP": "93.05", "intraDayHighLow": {"max": 81.25, "value": 79.5, "min": 77.35}, "open": 78.75, "change": 1.9500000000000028}, "preOpenMarket": {"preopen": [{"iep": true, "price": 0, "buyQty": 0, "sellQty": 0}, {"price": 76.05, "buyQty": 15, "sellQty": 0}, {"price": 76.25, "buyQty": 1, "sellQty": 0}, {"price": 76.3, "buyQty": 10, "sellQty": 0}, {"price": 76.35, "buyQty": 15, "sellQty": 0}, {"price": 76.65, "buyQty": 350, "sellQty": 0}, {"price": 78.9, "buyQty": 0, "sellQty": 1}, {"price": 79.45, "buyQty": 0, "sellQty": 2277}, {"price": 79.5, "buyQty": 0, "sellQty": 115}, {"price": 79.6, "buyQty": 0, "sellQty": 500}, {"price": 79.7, "buyQty": 0, "sellQty": 1475}], "totalBuyQuantity": 6974, "totalSellQuantity": 7470, "lastUpdateTime": "18-Sep-2020 09:07:19", "ato": {"sell": 0, "buy": 0}, "atoBuyQty": 0, "finalPrice": 78, "atoSellQty": 0, "finalQuantity": 0, "totalTradedVolume": 0, "IEP": 0}, "marketDeptOrderBook": {"totalSellQuantity": 356, "totalBuyQuantity": 0, "bid": [{"price": 0, "quantity": 0}, {"price": 0, "quantity": 0}, {"price": 0, "quantity": 0}, {"price": 0, "quantity": 0}, {"price": 0, "quantity": 0}], "valueAtRisk": {"applicableMargin": 40, "extremeLossMargin": 3.5, "adhocMargin": 11.31, "indexVar": 0, "securityVar": 25.19, "varMargin": 25.19}, "tradeInfo": {"totalMarketCap": 10990.88, "impactCost": 1.16, "totalTradedVolume": 15364, "ffmc": 5382.141625, "totalTradedValue": 12.13}, "ask": [{"price": 79.45, "quantity": 356}, {"price": 0, "quantity": 0}, {"price": 0, "quantity": 0}, {"price": 0, "quantity": 0}, {"price": 0, "quantity": 0}]}, "noBlockDeals": true, "language": {"shortNamePunjabi": "\u0a38\u0a3c\u0a4d\u0a30\u0a47\u0a2f\u0a28\u0a1c\u0a3c \u0a07\u0a70\u0a21\u0a38\u0a1f\u0a30\u0a40\u0a1c\u0a3c ", "shortName": "Shreyans Industries ", "shortNameHindi": "\u0936\u094d\u0930\u0947\u092f\u093e\u0902\u0938 \u0907\u0902\u0921\u0938\u094d\u091f\u094d\u0930\u0940\u091c  ", "nameHindi": "\u0936\u094d\u0930\u0947\u092f\u093e\u0902\u0938 \u0907\u0902\u0921\u0938\u094d\u091f\u094d\u0930\u0940\u091c  \u0932\u093f\u092e\u093f\u091f\u0947\u0921", "namePunjabi": "\u0a38\u0a3c\u0a4d\u0a30\u0a47\u0a2f\u0a28\u0a1c\u0a3c \u0a07\u0a70\u0a21\u0a38\u0a1f\u0a30\u0a40\u0a1c\u0a3c \u0a32\u0a3f\u0a2e\u0a1f\u0a3f\u0a21"}, "bulkBlockDeals": [{"name": "Session I"}, {"name": "Session II"}], "securityWiseDP": {"seriesRemarks": null, "quantityTraded": 15364, "secWiseDelPosDate": "18-SEP-2020 EOD", "deliveryToTradedQuantity": 60.45, "deliveryQuantity": 9288}, "securityInfo": {"derivatives": "No", "surveillance": "-", "sessionNo": "-", "classOfShare": "Equity", "faceValue": 10, "tradingStatus": "Active", "issuedCap": 13825000, "tradingSegment": "Normal Market", "boardStatus": "Main", "slb": "No"}, "metadata": {"status": "Listed", "lastUpdateTime": "18-Sep-2020 16:00:00", "listingDate": "06-Nov-1996", "series": "EQ", "symbol": "SHREYANIND", "pdSymbolPe": 3.8, "pdSectorPe": 38.45, "pdSectorInd": "NIFTY 500                                         ", "isin": "INE231C01019", "industry": "PAPER AND PAPER PRODUCTS"}}