{"info": {"isCASec": false, "isDelisted": false, "tempSuspendedSeries": ["BE"], "companyName": "Alicon Castalloy Limited", "industry": "AUTO ANCILLARIES", "symbol": "ALICON", "isSuspended": false, "isDebtSec": false, "isTop10": false, "debtSeries": [], "isETFSec": false, "isSLBSec": false, "isin": "INE062D01024", "isFNOSec": false, "identifier": "ALICONEQN", "activeSeries": ["EQ"]}, "priceInfo": {"pPriceBand": "20", "lastPrice": 342.8, "previousClose": 340.35, "weekHighLow": {"maxDate": "17-Jan-2020", "max": 450.45, "minDate": "24-Mar-2020", "value": 342.8, "min": 157.1}, "vwap": 342.93, "pChange": 0.719847216101069, "lowerCP": "272.30", "basePrice": 340.35, "close": 0, "upperCP": "408.40", "intraDayHighLow": {"max": 344.8, "value": 342.8, "min": 335.15}, "open": 340.05, "change": 2.4499999999999886}, "preOpenMarket": {"preopen": [{"iep": true, "price": 0, "buyQty": 0, "sellQty": 0}, {"price": 322.1, "buyQty": 150, "sellQty": 0}, {"price": 326.7, "buyQty": 8, "sellQty": 0}, {"price": 330, "buyQty": 2, "sellQty": 0}, {"price": 331, "buyQty": 15, "sellQty": 0}, {"price": 331.05, "buyQty": 20, "sellQty": 0}, {"price": 349.5, "buyQty": 0, "sellQty": 5}, {"price": 350, "buyQty": 0, "sellQty": 650}, {"price": 354, "buyQty": 0, "sellQty": 25}, {"price": 355, "buyQty": 0, "sellQty": 513}, {"price": 356, "buyQty": 0, "sellQty": 25}], "totalBuyQuantity": 1501, "totalSellQuantity": 3072, "lastUpdateTime": "18-Sep-2020 09:07:22", "ato": {"sell": 0, "buy": 0}, "atoBuyQty": 0, "finalPrice": 345, "atoSellQty": 0, "finalQuantity": 0, "totalTradedVolume": 0, "IEP": 0}, "marketDeptOrderBook": {"totalSellQuantity": 0, "totalBuyQuantity": 0, "bid": [{"price": 0, "quantity": 0}, {"price": 0, "quantity": 0}, {"price": 0, "quantity": 0}, {"price": 0, "quantity": 0}, {"price": 0, "quantity": 0}], "valueAtRisk": {"applicableMargin": 80, "extremeLossMargin": 3.5, "adhocMargin": 54.37, "indexVar": 0, "securityVar": 22.13, "varMargin": 22.13}, "tradeInfo": {"totalMarketCap": 47683.89, "impactCost": 1.58, "totalTradedVolume": 3122, "ffmc": 8907.8886215, "totalTradedValue": 10.71}, "ask": [{"price": 0, "quantity": 0}, {"price": 0, "quantity": 0}, {"price": 0, "quantity": 0}, {"price": 0, "quantity": 0}, {"price": 0, "quantity": 0}]}, "noBlockDeals": true, "language": {"shortNamePunjabi": "\u0a10\u0a32\u0a3f\u0a15\u0a28 \u0a15\u0a48\u0a38\u0a1f\u0a32\u0a4b\u0a08", "shortName": "Alicon Castalloy ", "shortNameHindi": "\u0910\u0932\u0940\u0915\u0949\u0928 \u0915\u0938\u094d\u091f\u093e\u0932\u094b\u092f ", "nameHindi": "\u0910\u0932\u0940\u0915\u0949\u0928 \u0915\u0938\u094d\u091f\u093e\u0932\u094b\u092f \u0932\u093f\u092e\u093f\u091f\u0947\u0921", "namePunjabi": "\u0a10\u0a32\u0a3f\u0a15\u0a28 \u0a15\u0a48\u0a38\u0a1f\u0a32\u0a4b\u0a08"}, "bulkBlockDeals": [{"name": "Session I"}, {"name": "Session II"}], "securityWiseDP": {"seriesRemarks": null, "quantityTraded": 2891, "secWiseDelPosDate": "18-SEP-2020 15:00:00", "deliveryToTradedQuantity": 68.77, "deliveryQuantity": 1988}, "securityInfo": {"derivatives": "No", "surveillance": "LT-ASM-Stage I", "sessionNo": "-", "classOfShare": "Equity", "faceValue": 5, "tradingStatus": "Active", "issuedCap": 13910121, "tradingSegment": "Normal Market", "boardStatus": "Main", "slb": "No"}, "metadata": {"status": "Listed", "lastUpdateTime": "18-Sep-2020 16:00:00", "listingDate": "29-Sep-2006", "series": "EQ", "symbol": "ALICON", "pdSymbolPe": 0, "pdSectorPe": 12.17, "pdSectorInd": "NIFTY METAL                                       ", "isin": "INE062D01024", "industry": "CASTINGS/FORGINGS"}}