{"info": {"isCASec": false, "isDelisted": false, "tempSuspendedSeries": ["IL"], "companyName": "Maruti Suzuki India Limited", "industry": "AUTOMOBILES - 4 WHEELERS", "symbol": "MARUTI", "isSuspended": false, "isDebtSec": false, "isTop10": false, "debtSeries": [], "isETFSec": false, "isSLBSec": true, "isin": "INE585B01010", "isFNOSec": true, "identifier": "MARUTIEQN", "activeSeries": ["EQ"]}, "priceInfo": {"pPriceBand": "No Band", "lastPrice": 6956.75, "previousClose": 7085.85, "weekHighLow": {"maxDate": "29-Oct-2019", "max": 7758.7, "minDate": "03-Apr-2020", "value": 6956.75, "min": 4001.1}, "vwap": 7018.94, "pChange": -1.8219409104059547, "lowerCP": "6377.30", "basePrice": 7085.85, "close": 0, "upperCP": "7794.40", "intraDayHighLow": {"max": 7149, "value": 6956.75, "min": 6931.6}, "open": 7148, "change": -129.10000000000036}, "preOpenMarket": {"preopen": [{"price": 6448.15, "buyQty": 0, "sellQty": 43}, {"price": 6500, "buyQty": 0, "sellQty": 5}, {"price": 6731.55, "buyQty": 0, "sellQty": 18}, {"price": 6833.9, "buyQty": 0, "sellQty": 9}, {"iep": true, "price": 7148, "buyQty": 0, "sellQty": 0}, {"price": 7250, "buyQty": 1, "sellQty": 0}, {"price": 7275, "buyQty": 1, "sellQty": 0}, {"price": 7291, "buyQty": 248, "sellQty": 0}, {"price": 7300, "buyQty": 1, "sellQty": 0}], "totalBuyQuantity": 5682, "totalSellQuantity": 12681, "lastUpdateTime": "18-Sep-2020 09:07:18", "ato": {"sell": 95, "buy": 696}, "atoBuyQty": 696, "finalPrice": 7148, "atoSellQty": 95, "finalQuantity": 2973, "totalTradedVolume": 2973, "IEP": 7148}, "marketDeptOrderBook": {"totalSellQuantity": 565, "totalBuyQuantity": 0, "bid": [{"price": 0, "quantity": 0}, {"price": 0, "quantity": 0}, {"price": 0, "quantity": 0}, {"price": 0, "quantity": 0}, {"price": 0, "quantity": 0}], "valueAtRisk": {"applicableMargin": 20.36, "extremeLossMargin": 3.5, "adhocMargin": 0, "indexVar": 0, "securityVar": 16.86, "varMargin": 16.86}, "tradeInfo": {"totalMarketCap": 21014954.57, "impactCost": 0.04, "totalTradedVolume": 1143560, "ffmc": 9257213.230694, "totalTradedValue": 80265.79}, "ask": [{"price": 6964.75, "quantity": 565}, {"price": 0, "quantity": 0}, {"price": 0, "quantity": 0}, {"price": 0, "quantity": 0}, {"price": 0, "quantity": 0}]}, "noBlockDeals": true, "language": {"shortNamePunjabi": "\u0a2e\u0a3e\u0a30\u0a42\u0a24\u0a40 \u0a38\u0a5b\u0a42\u0a15\u0a40 ", "shortName": "Maruti Suzuki", "shortNameHindi": "\u092e\u093e\u0930\u0942\u0924\u093f \u0938\u0941\u091c\u0941\u0915\u0940  ", "nameHindi": "\u092e\u093e\u0930\u0942\u0924\u093f \u0938\u0941\u091c\u0941\u0915\u0940 \u0932\u093f\u092e\u093f\u091f\u0947\u0921 ", "namePunjabi": "\u0a2e\u0a3e\u0a30\u0a42\u0a24\u0a40 \u0a38\u0a5b\u0a42\u0a15\u0a40 \u0a32\u0a3f\u0a2e\u0a3f\u0a1f\u0a3f\u0a21 "}, "bulkBlockDeals": [{"name": "Session I"}, {"name": "Session II"}], "securityWiseDP": {"seriesRemarks": null, "quantityTraded": 886104, "secWiseDelPosDate": "18-SEP-2020 15:00:00", "deliveryToTradedQuantity": 34.47, "deliveryQuantity": 305402}, "securityInfo": {"derivatives": "Yes", "surveillance": "-", "sessionNo": "-", "classOfShare": "Equity", "faceValue": 5, "tradingStatus": "Active", "issuedCap": 302080060, "tradingSegment": "Normal Market", "boardStatus": "Main", "slb": "Yes"}, "metadata": {"status": "Listed", "lastUpdateTime": "18-Sep-2020 16:00:00", "listingDate": "09-Jul-2003", "series": "EQ", "symbol": "MARUTI", "pdSymbolPe": 53.98, "pdSectorPe": 145.68, "pdSectorInd": "NIFTY AUTO                                        ", "isin": "INE585B01010", "industry": "PASSENGER/UTILITY VEHICLES"}}